luckyun_nacos/__init__.py
luckyun_nacos/client.py
tests/__init__.py
tests/test_client.py
luckyun_nacos-0.2.0.dist-info/METADATA
luckyun_nacos-0.2.0.dist-info/WHEEL
luckyun_nacos-0.2.0.dist-info/top_level.txt
luckyun_nacos-0.2.0.dist-info/RECORD
